[
  {
    "date": "2026-04-05",
    "median": 75,
    "low": 45,
    "high": 159,
    "lastPrice": 45,
    "sampleSize": 7
  },
  {
    "date": "2026-04-06",
    "median": 75,
    "low": 45,
    "high": 159,
    "lastPrice": 45,
    "sampleSize": 7
  },
  {
    "date": "2026-04-08",
    "median": 75,
    "low": 45,
    "high": 159,
    "lastPrice": 45,
    "sampleSize": 7
  },
  {
    "date": "2026-04-09",
    "median": 49.9,
    "low": 45,
    "high": 75,
    "lastPrice": 45,
    "sampleSize": 4
  },
  {
    "date": "2026-04-10",
    "median": 49.9,
    "low": 45,
    "high": 75,
    "lastPrice": 45,
    "sampleSize": 4
  },
  {
    "date": "2026-04-11",
    "median": 49.9,
    "low": 45,
    "high": 75,
    "lastPrice": 45,
    "sampleSize": 4
  },
  {
    "date": "2026-04-13",
    "median": 49.9,
    "low": 45,
    "high": 75,
    "lastPrice": 45,
    "sampleSize": 4
  },
  {
    "date": "2026-04-17",
    "median": 49.9,
    "low": 45,
    "high": 75,
    "lastPrice": 45,
    "sampleSize": 4
  },
  {
    "date": "2026-04-18",
    "median": 49.9,
    "low": 45,
    "high": 75,
    "lastPrice": 45,
    "sampleSize": 4
  }
]